agent_docstrings/__init__.py
agent_docstrings/__main__.py
agent_docstrings/cli.py
agent_docstrings/core.py
agent_docstrings/py.typed
agent_docstrings/bin/go_ast_parser.exe
agent_docstrings/bin/go_ast_parser_darwin_amd64
agent_docstrings/bin/go_ast_parser_darwin_arm64
agent_docstrings/bin/go_ast_parser_linux_amd64
agent_docstrings/example/example.py
agent_docstrings/languages/common.py
agent_docstrings/languages/delphi.py
agent_docstrings/languages/generic.py
agent_docstrings/languages/go.py
agent_docstrings/languages/java.py
agent_docstrings/languages/kotlin.py
agent_docstrings/languages/powershell.py
agent_docstrings/languages/python.py
agent_docstrings-1.3.5.dist-info/licenses/LICENSE
agent_docstrings-1.3.5.dist-info/METADATA
agent_docstrings-1.3.5.dist-info/WHEEL
agent_docstrings-1.3.5.dist-info/entry_points.txt
agent_docstrings-1.3.5.dist-info/top_level.txt
agent_docstrings-1.3.5.dist-info/RECORD
