Metadata-Version: 2.4
Name: agent-docstrings
Version: 1.3.5
Summary: A command-line tool to auto-generate and update file-level docstrings summarizing classes and functions. Useful for maintaining a high-level overview of your files, especially in projects with code generated or modified by AI assistants.
Author-email: Artemonim <Artemonim@yandex.ru>
Maintainer-email: Artemonim <Artemonim@yandex.ru>
License: MIT License
Project-URL: Homepage, https://github.com/Artemonim/AgentDocstrings
Project-URL: Source, https://github.com/Artemonim/AgentDocstrings
Project-URL: Tracker, https://github.com/Artemonim/AgentDocstrings/issues
Project-URL: Documentation, https://github.com/Artemonim/AgentDocstrings#readme
Project-URL: Changelog, https://github.com/Artemonim/AgentDocstrings/blob/master/CHANGELOG.md
Keywords: docstrings,documentation,ai,developer-tools,automation,code-generator,maintainability,code-quality,static-analysis,pre-commit,linter,summarize-code,code-navigation,refactoring,python,java,kotlin,go,powershell,delphi,typescript,javascript,csharp,c++,c
Classifier: Development Status :: 4 - Beta
Classifier: Environment :: Console
Classifier: Intended Audience :: Developers
Classifier: License :: OSI Approved :: MIT License
Classifier: Operating System :: OS Independent
Classifier: Programming Language :: Python :: 3
Classifier: Programming Language :: Python :: 3.10
Classifier: Programming Language :: Python :: 3.11
Classifier: Programming Language :: Python :: 3.12
Classifier: Programming Language :: Python :: 3.13
Classifier: Topic :: Software Development :: Documentation
Classifier: Topic :: Software Development :: Libraries :: Python Modules
Classifier: Topic :: Text Processing :: General
Classifier: Typing :: Typed
Requires-Python: >=3.10
License-File: LICENSE
Provides-Extra: dev
Requires-Dist: pytest>=6.0; extra == "dev"
Requires-Dist: pytest-cov>=2.0; extra == "dev"
Requires-Dist: black>=22.0; extra == "dev"
Requires-Dist: flake8>=4.0; extra == "dev"
Requires-Dist: mypy>=0.950; extra == "dev"
Requires-Dist: bump-my-version; extra == "dev"
Dynamic: license-file
